pyupgrade_docs.py
pyupgrade_docs-0.3.0.dist-info/LICENSE
pyupgrade_docs-0.3.0.dist-info/METADATA
pyupgrade_docs-0.3.0.dist-info/WHEEL
pyupgrade_docs-0.3.0.dist-info/entry_points.txt
pyupgrade_docs-0.3.0.dist-info/top_level.txt
pyupgrade_docs-0.3.0.dist-info/RECORD
