Metadata-Version: 2.1
Name: pyupgrade-docs
Version: 0.3.0
Summary: Run `pyupgrade` on python code blocks in documentation files
Home-page: https://github.com/verhovsky/pyupgrade-docs
Author: Boris Verkhovskiy
Author-email: boris.verk@gmail.com
License: MIT
Platform: UNKNOWN
Classifier: License :: OSI Approved :: MIT License
Classifier: Programming Language :: Python :: 3
Classifier: Programming Language :: Python :: 3 :: Only
Classifier: Programming Language :: Python :: 3.7
Classifier: Programming Language :: Python :: 3.8
Classifier: Programming Language :: Python :: 3.9
Classifier: Programming Language :: Python :: 3.10
Classifier: Programming Language :: Python :: Implementation :: CPython
Classifier: Programming Language :: Python :: Implementation :: PyPy
Requires-Python: >=3.7
License-File: LICENSE
Requires-Dist: pyupgrade (==2.31.1)
